pollination/breeam_daylight_4b/__init__.py
pollination/breeam_daylight_4b/_visualization.py
pollination/breeam_daylight_4b/entry.py
pollination_breeam_daylight_4b-1.0.9.dist-info/LICENSE
pollination_breeam_daylight_4b-1.0.9.dist-info/METADATA
pollination_breeam_daylight_4b-1.0.9.dist-info/WHEEL
pollination_breeam_daylight_4b-1.0.9.dist-info/top_level.txt
pollination_breeam_daylight_4b-1.0.9.dist-info/RECORD
